huaweicloudsdkges/__init__.py
huaweicloudsdkges/v1/__init__.py
huaweicloudsdkges/v1/ges_async_client.py
huaweicloudsdkges/v1/ges_client.py
huaweicloudsdkges/v1/model/__init__.py
huaweicloudsdkges/v1/model/attach_eip_request.py
huaweicloudsdkges/v1/model/attach_eip_response.py
huaweicloudsdkges/v1/model/backup.py
huaweicloudsdkges/v1/model/bind_eip_req.py
huaweicloudsdkges/v1/model/clear_graph_request.py
huaweicloudsdkges/v1/model/clear_graph_response.py
huaweicloudsdkges/v1/model/create_backup_request.py
huaweicloudsdkges/v1/model/create_backup_response.py
huaweicloudsdkges/v1/model/create_graph_req.py
huaweicloudsdkges/v1/model/create_graph_request.py
huaweicloudsdkges/v1/model/create_graph_response.py
huaweicloudsdkges/v1/model/create_metadata_req.py
huaweicloudsdkges/v1/model/create_metadata_request.py
huaweicloudsdkges/v1/model/create_metadata_response.py
huaweicloudsdkges/v1/model/data_source.py
huaweicloudsdkges/v1/model/delete_backup_request.py
huaweicloudsdkges/v1/model/delete_backup_response.py
huaweicloudsdkges/v1/model/delete_graph_request.py
huaweicloudsdkges/v1/model/delete_graph_response.py
huaweicloudsdkges/v1/model/delete_metadata_request.py
huaweicloudsdkges/v1/model/delete_metadata_response.py
huaweicloudsdkges/v1/model/detach_eip_request.py
huaweicloudsdkges/v1/model/detach_eip_response.py
huaweicloudsdkges/v1/model/edgeset_path.py
huaweicloudsdkges/v1/model/edgeset_path1.py
huaweicloudsdkges/v1/model/encryption_req.py
huaweicloudsdkges/v1/model/expand_graph_req.py
huaweicloudsdkges/v1/model/expand_graph_request.py
huaweicloudsdkges/v1/model/expand_graph_response.py
huaweicloudsdkges/v1/model/export_graph_req.py
huaweicloudsdkges/v1/model/export_graph_request.py
huaweicloudsdkges/v1/model/export_graph_response.py
huaweicloudsdkges/v1/model/ges_meta_data.py
huaweicloudsdkges/v1/model/ges_quota_resp.py
huaweicloudsdkges/v1/model/graph.py
huaweicloudsdkges/v1/model/graph1.py
huaweicloudsdkges/v1/model/graph_size_type_index_req.py
huaweicloudsdkges-3.1.184.dist-info/METADATA
huaweicloudsdkges-3.1.184.dist-info/WHEEL
huaweicloudsdkges-3.1.184.dist-info/licenses/LICENSE
huaweicloudsdkges-3.1.184.dist-info/RECORD
